{
 "storyId": "603_ko-kr",
 "pages": [
   {
     "pageNumber": 0,
     "texts": ["깨끗한 우리 마을"]
   },
   {
     "pageNumber": 1,
     "texts": ["좋은 아침"]
   },
   {
     "pageNumber": 2,
     "texts": ["길에 쓰레기가 많아"]
   },
   {
     "pageNumber": 3,
     "texts": ["우리 함께 청소하자"]
   },
   {
     "pageNumber": 4,
     "texts": ["쓰레기를 쓰레기통에 버려"]
   },
   {
     "pageNumber": 5,
     "texts": ["우리 학교도 깨끗하게 청소하자"]
   },
   {
     "pageNumber": 6,
     "texts": ["어떤 쓰레기는 함께 모아야 해요"]
   },
   {
     "pageNumber": 7,
     "texts": ["플라스틱 쓰레기는 다른 쓰레기통에 따로 모아야 해요"]
   },
   {
     "pageNumber": 8,
     "texts": ["음식물 쓰레기는 따로 모아야 해요"]
   },
   {
     "pageNumber": 9,
     "texts": ["쓰레기를 함부로 버리지 마세요"]
   },
   {
     "pageNumber": 10,
     "texts": ["깨끗한 동네, 행복한 삶"]
   },
   {
     "pageNumber": 11,
     "texts": ["우리 환경을 돌봐요"]
   }
 ],
 "title": "603 Ko-kr"
}